LICENSE
README.md
setup.cfg
setup.py
ducksearch/__init__.py
ducksearch/__version__.py
ducksearch.egg-info/PKG-INFO
ducksearch.egg-info/SOURCES.txt
ducksearch.egg-info/dependency_links.txt
ducksearch.egg-info/requires.txt
ducksearch.egg-info/top_level.txt
ducksearch/decorators/__init__.py
ducksearch/decorators/execute_with_duckdb.py
ducksearch/delete/__init__.py
ducksearch/delete/documents.py
ducksearch/delete/delete/documents.sql
ducksearch/delete/delete/documents_queries.sql
ducksearch/delete/delete/scores.sql
ducksearch/delete/update/df.sql
ducksearch/delete/update/docs.sql
ducksearch/delete/update/scores.sql
ducksearch/delete/update/stats.sql
ducksearch/delete/update/terms.sql
ducksearch/evaluation/__init__.py
ducksearch/evaluation/evaluation.py
ducksearch/hf/__init__.py
ducksearch/hf/insert.py
ducksearch/hf/drop/tmp.sql
ducksearch/hf/insert/documents.sql
ducksearch/hf/insert/tmp.sql
ducksearch/hf/select/columns.sql
ducksearch/hf/select/exists.sql
ducksearch/search/__init__.py
ducksearch/search/create.py
ducksearch/search/graphs.py
ducksearch/search/select.py
ducksearch/search/create/index.sql
ducksearch/search/create/queries_index.sql
ducksearch/search/create/settings.sql
ducksearch/search/create/stopwords.sql
ducksearch/search/create/tables.sql
ducksearch/search/drop/_documents.sql
ducksearch/search/drop/queries.sql
ducksearch/search/drop/schema.sql
ducksearch/search/drop/scores.sql
ducksearch/search/insert/dict.sql
ducksearch/search/insert/docs.sql
ducksearch/search/insert/queries.sql
ducksearch/search/insert/settings.sql
ducksearch/search/insert/terms.sql
ducksearch/search/select/search.sql
ducksearch/search/select/search_filters.sql
ducksearch/search/select/search_graph.sql
ducksearch/search/select/search_graph_filters.sql
ducksearch/search/select/search_order_by.sql
ducksearch/search/select/settings.sql
ducksearch/search/select/settings_exists.sql
ducksearch/search/select/stats.sql
ducksearch/search/select/termids_to_score.sql
ducksearch/search/update/bm25id.sql
ducksearch/search/update/dict.sql
ducksearch/search/update/scores.sql
ducksearch/search/update/stats.sql
ducksearch/tables/__init__.py
ducksearch/tables/create.py
