Metadata-Version: 2.1
Name: ducksearch
Version: 1.0.2
Summary: DuckSearch: A Python library for efficient search in large collections of text data.
Home-page: https://github.com/lightonai/ducksearch
Author: LightOn
License: MIT
Classifier: Programming Language :: Python :: 3
Classifier: Operating System :: OS Independent
Requires-Python: >=3.8
License-File: LICENSE
Requires-Dist: pandas>=2.2.1
Requires-Dist: duckdb>=1.0.0
Requires-Dist: pyarrow>=16.1.0
Requires-Dist: tqdm>=4.66.4
Requires-Dist: joblib>=1.4.2
Provides-Extra: eval
Requires-Dist: pandas>=2.2.1; extra == "eval"
Requires-Dist: duckdb>=1.0.0; extra == "eval"
Requires-Dist: pyarrow>=16.1.0; extra == "eval"
Requires-Dist: tqdm>=4.66.4; extra == "eval"
Requires-Dist: joblib>=1.4.2; extra == "eval"
Requires-Dist: ranx>=0.3.16; extra == "eval"
Requires-Dist: beir>=2.0.0; extra == "eval"
Provides-Extra: dev
Requires-Dist: pandas>=2.2.1; extra == "dev"
Requires-Dist: duckdb>=1.0.0; extra == "dev"
Requires-Dist: pyarrow>=16.1.0; extra == "dev"
Requires-Dist: tqdm>=4.66.4; extra == "dev"
Requires-Dist: joblib>=1.4.2; extra == "dev"
Requires-Dist: sqlfluff>=3.1.0; extra == "dev"
Requires-Dist: ruff>=0.4.9; extra == "dev"
Requires-Dist: pytest-cov>=5.0.0; extra == "dev"
Requires-Dist: pytest>=8.2.1; extra == "dev"
Requires-Dist: harlequin>=1.24.0; extra == "dev"
Requires-Dist: mkdocs-material==9.5.32; extra == "dev"
Requires-Dist: mkdocs-awesome-pages-plugin==2.9.3; extra == "dev"
Requires-Dist: mkdocs-jupyter==0.24.8; extra == "dev"
Requires-Dist: mkdocs_charts_plugin==0.0.10; extra == "dev"
Requires-Dist: numpydoc==1.8.0; extra == "dev"
Requires-Dist: ranx>=0.3.16; extra == "dev"
Requires-Dist: beir>=2.0.0; extra == "dev"
